viz_lower_limb/__init__.py
viz_lower_limb/dashboard.py
viz_lower_limb/definitions.py
viz_lower_limb-0.1.0.dist-info/METADATA
viz_lower_limb-0.1.0.dist-info/WHEEL
viz_lower_limb-0.1.0.dist-info/RECORD
